{
  "id": "sunjin",
  "primary_name": "孫瑾",
  "courtesy_name": null,
  "given_name": null,
  "aliases": [],
  "other_names": [],
  "birth_ad": null,
  "death_ad": 280,
  "brief": "孫皓太子",
  "bio_chapters": [],
  "mentions_by_work": {
    "zztj": [
      {
        "chapter_id": "zztj.60",
        "chapter_title": "漢紀五十二",
        "book_title": "資治通鑑",
        "work": "zztj",
        "anchor": "zztj.60.p79",
        "at": 317,
        "data_url": "data/zztj/zztj/60.json",
        "matched": "孫瑾",
        "snippet": "…前與袁紹等謀稱尊號，脅訓斬虞及妻子於薊市。故常山相孫瑾、掾張逸、張瓚等相與就虞，罵瓚極口，然後同死，瓚傳虞首於京師，故吏尾敦於路劫虞首，歸葬之。虞以恩厚得眾心，北州百姓流舊莫不痛惜…"
      }
    ],
    "sanguozhi": [],
    "houhanshu": []
  },
  "n_mentions": 1
}
