{
  "id": "xuhuang",
  "primary_name": "徐晃",
  "courtesy_name": "公明",
  "given_name": null,
  "aliases": [],
  "other_names": [],
  "birth_ad": null,
  "death_ad": 227,
  "brief": "曹魏右將軍",
  "bio_chapters": [
    {
      "chapter_id": "wei.17",
      "title": "魏書·張樂于張徐傳",
      "book_title": "魏書",
      "work": "sanguozhi",
      "data_url": "data/sanguozhi/wei/17.json"
    }
  ],
  "mentions_by_work": {
    "zztj": [
      {
        "chapter_id": "zztj.63",
        "chapter_title": "漢紀五十五",
        "book_title": "資治通鑑",
        "work": "zztj",
        "anchor": "zztj.63.p33",
        "at": 381,
        "data_url": "data/zztj/zztj/63.json",
        "matched": "徐晃",
        "snippet": "…而輕敵。擊，可破也！」操曰：「誰可使者？」攸曰：「徐晃可。」乃遣偏將軍河東徐晃與史渙邀擊猛，破走之，燒其輜重。"
      },
      {
        "chapter_id": "zztj.64",
        "chapter_title": "漢紀五十六",
        "book_title": "資治通鑑",
        "work": "zztj",
        "anchor": "zztj.64.p10",
        "at": 149,
        "data_url": "data/zztj/zztj/64.json",
        "matched": "徐晃",
        "snippet": "…將沮鵠於邯鄲，拔之。易陽令韓范、涉長梁岐皆舉縣降。徐晃言於操曰：「二袁未破，諸城未下者傾耳而聽，宜旌賞二縣以示諸城。」操從之，范、岐皆賜爵關內侯。黑山賊帥張燕遣使求助，操拜平北將軍…"
      },
      {
        "chapter_id": "zztj.65",
        "chapter_title": "漢紀五十七",
        "book_title": "資治通鑑",
        "work": "zztj",
        "anchor": "zztj.65.p56",
        "at": 329,
        "data_url": "data/zztj/zztj/65.json",
        "matched": "徐晃",
        "snippet": "…軍兼以饑疫，死者太半。操乃留征南將軍曹仁、橫野將軍徐晃守江陵，折衝將軍樂進守襄陽，引軍北還。"
      },
      {
        "chapter_id": "zztj.66",
        "chapter_title": "漢紀五十八",
        "book_title": "資治通鑑",
        "work": "zztj",
        "anchor": "zztj.66.p29",
        "at": 24,
        "data_url": "data/zztj/zztj/66.json",
        "matched": "徐晃",
        "snippet": "八月，操至潼關，與超等夾關而軍。操急持之，而潛遣徐晃、朱靈以步騎四千人渡浦阪津，據河西為營。閏月，操自潼關北渡河。兵眾先渡，操獨與虎士百餘人留南岸斷後。馬超將步騎萬餘人攻之，矢下…"
      },
      {
        "chapter_id": "zztj.67",
        "chapter_title": "漢紀五十九",
        "book_title": "資治通鑑",
        "work": "zztj",
        "anchor": "zztj.67.p31",
        "at": 288,
        "data_url": "data/zztj/zztj/67.json",
        "matched": "徐晃",
        "snippet": "…定，未可擊也。」乃還。以夏侯淵為都護將軍，督張郃、徐晃等守漢中；以丞相長史杜襲為駙馬都尉，留督漢中事。襲綏懷開導，百姓自樂出徙洛、鄴者八萬餘口。"
      },
      {
        "chapter_id": "zztj.68",
        "chapter_title": "漢紀六十",
        "book_title": "資治通鑑",
        "work": "zztj",
        "anchor": "zztj.68.p19",
        "at": 14,
        "data_url": "data/zztj/zztj/68.json",
        "matched": "徐晃",
        "snippet": "劉備屯陽平關，夏侯淵、張郃、徐晃等與之相拒。備遣其將陳式等絕馬鳴閣道，徐晃擊破之。張郃屯廣石，備攻之不能克，急書發益州兵。諸葛亮以問從事犍為楊洪，洪曰：「漢中…"
      },
      {
        "chapter_id": "zztj.68",
        "chapter_title": "漢紀六十",
        "book_title": "資治通鑑",
        "work": "zztj",
        "anchor": "zztj.68.p39",
        "at": 14,
        "data_url": "data/zztj/zztj/68.json",
        "matched": "徐晃",
        "snippet": "魏王操之出漢中也，使平寇將軍徐晃屯宛以助曹仁；及于禁陷沒，晃前至陽陵陂。關羽遣兵屯偃城，晃既到，詭道作都塹，示欲截其後，羽兵燒屯走。晃得偃城，連營稍前。操使趙…"
      },
      {
        "chapter_id": "zztj.68",
        "chapter_title": "漢紀六十",
        "book_title": "資治通鑑",
        "work": "zztj",
        "anchor": "zztj.68.p47",
        "at": 27,
        "data_url": "data/zztj/zztj/68.json",
        "matched": "徐晃",
        "snippet": "…之稱籓也，魏王操召張遼等諸軍悉還救樊，未至而圍解。徐晃振旅還摩陂，操迎晃七里，置酒大會。王舉酒謂晃曰：「全樊、襄陽，將軍之功也。」亦厚賜桓階，以為尚書。操嫌荊州殘民及其屯田在漢川者…"
      },
      {
        "chapter_id": "zztj.69",
        "chapter_title": "第六十九卷 魏紀一",
        "book_title": "資治通鑑",
        "work": "zztj",
        "anchor": "zztj.69.p18",
        "at": 169,
        "data_url": "data/zztj/zztj/69.json",
        "matched": "徐晃",
        "snippet": "…變態，為國生患。」王不聽。遣征南將軍夏侯尚、右將軍徐晃與達共襲劉封。上庸太守申耽叛封來降，封破，走還成都。"
      },
      {
        "chapter_id": "zztj.69",
        "chapter_title": "第六十九卷 魏紀一",
        "book_title": "資治通鑑",
        "work": "zztj",
        "anchor": "zztj.69.p89",
        "at": 63,
        "data_url": "data/zztj/zztj/69.json",
        "matched": "徐晃",
        "snippet": "…軍大將軍曹真、征南大將軍夏侯尚、左將軍張郃、右將軍徐晃圍南郡。吳建威將軍呂範督五軍，以舟軍拒休等，左將軍諸葛瑾、平北將軍潘璋、將軍楊粲救南郡，裨將軍朱桓以濡須督拒曹仁。"
      }
    ],
    "sanguozhi": [
      {
        "chapter_id": "shu.10",
        "chapter_title": "蜀書·劉彭廖李劉魏楊傳",
        "book_title": "蜀書",
        "work": "sanguozhi",
        "anchor": "shu.10.p2",
        "at": 337,
        "data_url": "data/sanguozhi/shu/10.json",
        "matched": "徐晃",
        "snippet": "…新城郡，以〕達領新城太守。遣征南將軍夏侯尚、右將軍徐晃與達共襲封。達與封書曰："
      },
      {
        "chapter_id": "shu.6",
        "chapter_title": "蜀書·關張馬黃趙傳",
        "book_title": "蜀書",
        "work": "sanguozhi",
        "anchor": "shu.6.p5",
        "at": 269,
        "data_url": "data/sanguozhi/shu/06.json",
        "matched": "徐晃",
        "snippet": "…懼不安。於是權陰誘芳、仁，芳、仁使人迎權。而曹公遣徐晃救曹仁，羽不能克，引軍退還。權已據江陵，盡虜羽士眾妻子，羽軍遂散。權遣將逆擊羽，斬羽及子平於臨沮。"
      },
      {
        "chapter_id": "wei.1",
        "chapter_title": "魏書·武帝紀",
        "book_title": "魏書",
        "work": "sanguozhi",
        "anchor": "wei.1.p118",
        "at": 46,
        "data_url": "data/sanguozhi/wei/01.json",
        "matched": "徐晃",
        "snippet": "…羽。八月，漢水溢，灌禁軍，軍沒，羽獲禁，遂圍仁。使徐晃救之。"
      },
      {
        "chapter_id": "wei.1",
        "chapter_title": "魏書·武帝紀",
        "book_title": "魏書",
        "work": "sanguozhi",
        "anchor": "wei.1.p51",
        "at": 17,
        "data_url": "data/sanguozhi/wei/01.json",
        "matched": "徐晃",
        "snippet": "袁紹運穀車數千乘至，公用荀攸計，遣徐晃、史渙邀擊，大破之，盡燒其車。公與紹相拒連月，雖比戰斬將，然衆少糧盡，士卒疲乏。公謂運者曰：「却十五日爲汝破紹，不復勞汝矣。」…"
      },
      {
        "chapter_id": "wei.1",
        "chapter_title": "魏書·武帝紀",
        "book_title": "魏書",
        "work": "sanguozhi",
        "anchor": "wei.1.p76",
        "at": 45,
        "data_url": "data/sanguozhi/wei/01.json",
        "matched": "徐晃",
        "snippet": "…，置官屬，爲丞相副。太原商曜等以大陵叛，遣夏侯淵、徐晃圍破之。張魯據漢中，三月，遣鍾繇討之。公使淵等出河東與繇會。"
      },
      {
        "chapter_id": "wei.1",
        "chapter_title": "魏書·武帝紀",
        "book_title": "魏書",
        "work": "sanguozhi",
        "anchor": "wei.1.p77",
        "at": 85,
        "data_url": "data/sanguozhi/wei/01.json",
        "matched": "徐晃",
        "snippet": "…」秋七月，公西征，與超等夾關而軍。公急持之，而潛遣徐晃、朱靈等夜渡蒲阪津，據河西爲營。公自潼關北渡，未濟，超赴船急戰。校尉丁斐因放牛馬以餌賊，賊亂取牛馬，公乃得渡，循河爲甬道而南。…"
      },
      {
        "chapter_id": "wei.10",
        "chapter_title": "魏書·荀彧荀攸賈詡傳",
        "book_title": "魏書",
        "work": "sanguozhi",
        "anchor": "wei.10.p31",
        "at": 175,
        "data_url": "data/sanguozhi/wei/10.json",
        "matched": "徐晃",
        "snippet": "…鋭而輕敵，撃可破也。」太祖曰：「誰可使？」攸曰：「徐晃可。」乃遣晃及史渙邀撃破走之，燒其輜重。會許攸來降，言紹遣淳于瓊等將萬餘兵迎運糧，將驕卒惰，可要撃也。衆皆疑。唯攸與賈詡勸太祖…"
      },
      {
        "chapter_id": "wei.14",
        "chapter_title": "魏書·程郭董劉蔣劉傳",
        "book_title": "魏書",
        "work": "sanguozhi",
        "anchor": "wei.14.p36",
        "at": 217,
        "data_url": "data/sanguozhi/wei/14.json",
        "matched": "徐晃",
        "snippet": "…自恃二城守固，必不速退。」太祖曰：「善。」即敕救將徐晃以權書射著圍裡及羽屯中，圍裡聞之，志氣百倍。羽果猶豫。權軍至，得其二城，羽乃破敗。"
      },
      {
        "chapter_id": "wei.22",
        "chapter_title": "魏書·桓二陈徐卫卢传",
        "book_title": "魏書",
        "work": "sanguozhi",
        "anchor": "wei.22.p3",
        "at": 152,
        "data_url": "data/sanguozhi/wei/22.json",
        "matched": "徐晃",
        "snippet": "…，多此類也。遷尚書，典選舉。曹仁爲關羽所圍，太祖遣徐晃救之，不解。太祖欲自南征，以问羣下。羣下皆謂：「王不亟行，今敗矣。」階獨曰：「大王以仁等爲足以料事勢不也？」曰：「能。」「大王…"
      },
      {
        "chapter_id": "wei.23",
        "chapter_title": "魏書·和常楊杜趙裴傳",
        "book_title": "魏書",
        "work": "sanguozhi",
        "anchor": "wei.23.p23",
        "at": 28,
        "data_url": "data/sanguozhi/wei/23.json",
        "matched": "徐晃",
        "snippet": "…征南將軍曹仁於樊。儼以議郎參仁軍事南行，遷平寇將軍徐晃俱前。既到，羽圍仁遂堅，餘救兵未到。晃所督不足解圍，而諸將呵責晃促救。儼謂諸將曰：「今賊圍素固，水潦猶盛。我徒卒單少，而仁隔絕…"
      },
      {
        "chapter_id": "wei.26",
        "chapter_title": "魏書·滿田牽郭傳",
        "book_title": "魏書",
        "work": "sanguozhi",
        "anchor": "wei.26.p5",
        "at": 244,
        "data_url": "data/sanguozhi/wei/26.json",
        "matched": "徐晃",
        "snippet": "…宜待之。」仁曰：「善。」寵乃沈白馬，與軍人盟誓。會徐晃等救至，寵力戰有功，羽遂退。進封安昌亭侯。文帝即王位，遷揚武將軍。破吳於江陵有功，更拜伏波將軍，屯新野。大軍南征，到精湖，寵帥…"
      },
      {
        "chapter_id": "wei.4",
        "chapter_title": "魏書·三少帝紀",
        "book_title": "魏書",
        "work": "sanguozhi",
        "anchor": "wei.4.p9",
        "at": 94,
        "data_url": "data/sanguozhi/wei/04.json",
        "matched": "徐晃",
        "snippet": "…太常桓階、司空陳羣、太傅鍾繇、車騎將軍張郃、左將軍徐晃、前將軍張遼、右將軍樂進、太尉華歆、司徒王朗、驃騎將軍曹洪、征西將軍夏侯淵、後將軍朱靈、文聘、執金吾臧霸、破虜將軍李典、立義將…"
      },
      {
        "chapter_id": "wei.9",
        "chapter_title": "魏書·諸夏侯曹傳",
        "book_title": "魏書",
        "work": "sanguozhi",
        "anchor": "wei.9.p14",
        "at": 191,
        "data_url": "data/sanguozhi/wei/09.json",
        "matched": "徐晃",
        "snippet": "…，救兵不至。仁激厉將士，示以必死，將士感之皆無二。徐晃救至，水亦稍减，晃從外擊羽，仁得溃圍出，羽退走。"
      },
      {
        "chapter_id": "wei.9",
        "chapter_title": "魏書·諸夏侯曹傳",
        "book_title": "魏書",
        "work": "sanguozhi",
        "anchor": "wei.9.p15",
        "at": 148,
        "data_url": "data/sanguozhi/wei/09.json",
        "matched": "徐晃",
        "snippet": "…家。後召還屯宛。孫權遣將陳邵据襄陽，詔仁討之。仁與徐晃攻破邵，遂入襄陽，使將軍高遷等徙漢南附化民於漢北，文帝遣使即拜仁大將軍。又詔仁移屯临潁，遷大司馬，復督諸軍据烏江，還屯合肥。黃…"
      },
      {
        "chapter_id": "wei.9",
        "chapter_title": "魏書·諸夏侯曹傳",
        "book_title": "魏書",
        "work": "sanguozhi",
        "anchor": "wei.9.p21",
        "at": 154,
        "data_url": "data/sanguozhi/wei/09.json",
        "matched": "徐晃",
        "snippet": "…是時，夏侯淵沒於陽平，太祖憂之。以真爲征蜀護軍，督徐晃等破劉備别將高详於陽平。太祖自至漢中，拔出諸軍，使真至武都迎曹洪等還屯陳倉。文帝即王位，以真爲鎮西將軍，假節都督雍、涼州諸軍事…"
      },
      {
        "chapter_id": "wei.9",
        "chapter_title": "魏書·諸夏侯曹傳",
        "book_title": "魏書",
        "work": "sanguozhi",
        "anchor": "wei.9.p5",
        "at": 249,
        "data_url": "data/sanguozhi/wei/09.json",
        "matched": "徐晃",
        "snippet": "…，使淵督諸將擊廬江叛者雷緒，緒破，又行征西護軍，督徐晃擊太原賊，攻下二十餘屯，斬賊帥商曜，屠其城。從征韓遂等，戰於渭南。又督朱靈平隃糜、汧氐。與太祖會安定，降楊秋。"
      },
      {
        "chapter_id": "wei.9",
        "chapter_title": "魏書·諸夏侯曹傳",
        "book_title": "魏書",
        "work": "sanguozhi",
        "anchor": "wei.9.p7",
        "at": 222,
        "data_url": "data/sanguozhi/wei/09.json",
        "matched": "徐晃",
        "snippet": "…以淵畏之。會魯降，漢中平，以淵行都護將軍，督張郃、徐晃等平巴郡。太祖還鄴，留淵守漢中，即拜淵征西將軍。二十三年，劉備軍陽平關，淵率諸將拒之，相守連年。二十四年正月，備夜燒圍鹿角。淵…"
      },
      {
        "chapter_id": "wu.13",
        "chapter_title": "吳書·陆逊传",
        "book_title": "吳書",
        "work": "sanguozhi",
        "anchor": "wu.13.p5",
        "at": 44,
        "data_url": "data/sanguozhi/wu/13.json",
        "matched": "徐晃",
        "snippet": "…長世，雖昔晉文城濮之師，淮陰拔趙之略，蔑以尚茲。聞徐晃等少騎駐旌，窺望麾葆。操猾虜也，忿不思難，恐潛增眾，以逞其心。雖雲師老，猶有驍悍。且戰捷之後，常苦輕敵，古人杖術，軍勝彌警，願…"
      },
      {
        "chapter_id": "wu.2",
        "chapter_title": "吳書·吳主傳",
        "book_title": "吳書",
        "work": "sanguozhi",
        "anchor": "wu.2.p22",
        "at": 76,
        "data_url": "data/sanguozhi/wu/02.json",
        "matched": "徐晃",
        "snippet": "…張遼、臧霸出洞口，曹仁出濡須，曹眞、夏侯尚、張郃、徐晃圍南郡。權遣呂範等督五軍，以舟軍拒休等，諸葛瑾、潘璋、楊粲救南郡，朱桓以濡須督拒仁。時揚、越蠻夷多未平集，內難未弭，故權卑辭上…"
      },
      {
        "chapter_id": "wu.2",
        "chapter_title": "吳書·吳主傳",
        "book_title": "吳書",
        "work": "sanguozhi",
        "anchor": "wu.2.p8",
        "at": 300,
        "data_url": "data/sanguozhi/wu/02.json",
        "matched": "徐晃",
        "snippet": "…死者大半。備、瑜等復追至南郡。曹公遂北還，留曹仁、徐晃於江陵，使樂進守襄陽。時甘寧在夷陵，爲仁黨所圍，用呂蒙計，留淩統以拒仁，以其半救寧，軍以勝反。權自率眾圍合肥，使張昭攻九江之當…"
      }
    ],
    "houhanshu": []
  },
  "n_mentions": 30
}
